paebot/__init__.py
paebot-0.1.3.dist-info/LICENSE
paebot-0.1.3.dist-info/METADATA
paebot-0.1.3.dist-info/WHEEL
paebot-0.1.3.dist-info/top_level.txt
paebot-0.1.3.dist-info/RECORD
