Metadata-Version: 2.1
Name: paebot
Version: 0.1.3
Summary: mne paebot, tebe paebot, vsem paebot
Home-page: https://github.com/ebanull/paebot
Author: ebanull
License: MIT
License-File: LICENSE
Requires-Dist: requests
